grand/__init__.py
grand/test_graph.py
grand/backends/__init__.py
grand/backends/_dataframe.py
grand/backends/_dynamodb.py
grand/backends/_gremlin.py
grand/backends/_igraph.py
grand/backends/_networkit.py
grand/backends/_networkx.py
grand/backends/_sqlbackend.py
grand/backends/backend.py
grand/backends/metadatastore.py
grand/backends/test_backends.py
grand/backends/test_cached_backend.py
grand/backends/test_metadatastore.py
grand/dialects/__init__.py
grand/dialects/test_dialect.py
grand_graph-0.7.0.dist-info/METADATA
grand_graph-0.7.0.dist-info/WHEEL
grand_graph-0.7.0.dist-info/licenses/LICENSE
grand_graph-0.7.0.dist-info/RECORD
