Metadata-Version: 2.4
Name: grand-graph
Version: 0.7.0
Summary: Graph database wrapper for non-graph datastores
Author-email: Jordan Matelsky <opensource@matelsky.com>
License-File: LICENSE
Requires-Python: >=3.10
Requires-Dist: cachetools>=5.5.2
Requires-Dist: networkx>=2.4
Requires-Dist: numpy>=1.26.4
Requires-Dist: pandas>=2.2.3
Provides-Extra: dynamodb
Requires-Dist: boto3; extra == 'dynamodb'
Provides-Extra: igraph
Requires-Dist: igraph; extra == 'igraph'
Provides-Extra: networkit
Requires-Dist: cmake; extra == 'networkit'
Requires-Dist: cython; extra == 'networkit'
Requires-Dist: networkit; extra == 'networkit'
Requires-Dist: numpy<2.0.0; extra == 'networkit'
Provides-Extra: sql
Requires-Dist: sqlalchemy>=1.3; extra == 'sql'
